Workbook

Sheet Dashboard
A1: NorthStar Retail Group — Excel KPI Dashboard
A3: Total Revenue | C3: Total Profit | E3: Gross Margin % | G3: Orders in Sample
A4: =SUM('Transaction Sample'!I2:I501) -> 269045.39 | C4: =SUM('Transaction Sample'!K2:K501) -> 114604.76 | E4: =SUM('Transaction Sample'!K2:K501)/SUM('Transaction Sample'!I2:I501) -> 0.42596812 | G4: =COUNTA('Transaction Sample'!A2:A501) -> 500
A6: Note: KPI values above are computed from the 500-row transaction SAMPLE included in this workbook for demonstration; full 75,023-row figures ($31.1M revenue, 42.7% margin) are documented in the project README and SQL/Python analysis.

Sheet Transaction Sample
A1: order_id | B1: order_date | C1: order_status | D1: region | E1: category | F1: product_name | G1: quantity | H1: unit_price | I1: line_total | J1: line_cost | K1: profit | L1: order_month
A2: 520897 | B2: 2024-11-18 | C2: Completed | D2: Northeast | E2: Electronics | F2: CoreHome Wireless Earbuds Lite | G2: 1 | H2: 1236.32 | I2: 1236.32 | J2: 698.1 | K2: 538.22 | L2: 2024-11
A3: 532487 | B3: 2025-10-08 | C3: Completed | D3: Southwest | E3: Electronics | F3: HomeCraft Smart Watch Classic | G3: 1 | H3: 1240.3 | I3: 1240.3 | J3: 720.81 | K3: 519.49 | L3: 2025-10
A4: 516910 | B4: 2024-07-28 | C4: Completed | D4: Southwest | E4: Furniture | F4: Nexa Sofa | G4: 1 | H4: 354.35 | I4: 354.35 | J4: 211.76 | K4: 142.59 | L4: 2024-07
A5: 514114 | B5: 2024-04-14 | C5: Completed | D5: West | E5: Electronics | F5: Nexa Bluetooth Speaker Classic | G5: 1 | H5: 599.18 | I5: 599.18 | J5: 330.58 | K5: 268.6 | L5: 2024-04
A6: 508918 | B6: 2023-11-25 | C6: Completed | D6: Midwest | E6: Furniture | F6: Nexa Bookshelf X | G6: 1 | H6: 133.58 | I6: 133.58 | J6: 78.11 | K6: 55.47 | L6: 2023-11
A7: 525988 | B7: 2025-03-13 | C7: Completed | D7: Northeast | E7: Electronics | F7: Vantek Bluetooth Speaker Max | G7: 1 | H7: 155.78 | I7: 155.78 | J7: 88.45 | K7: 67.33 | L7: 2025-03
A8: 531704 | B8: 2025-09-13 | C8: Completed | D8: West | E8: Furniture | F8: PrimeLiving Desk Lite | G8: 1 | H8: 511.44 | I8: 511.44 | J8: 296.49 | K8: 214.95 | L8: 2025-09
A9: 532920 | B9: 2025-10-20 | C9: Completed | D9: Northeast | E9: Outdoor & Garden | F9: Lumeo Garden Tools Kit | G9: 1 | H9: 68.88 | I9: 68.88 | J9: 39.43 | K9: 29.45 | L9: 2025-10
A10: 528203 | B10: 2025-05-21 | C10: Completed | D10: Southwest | E10: Home Appliances | F10: PrimeLiving Air Fryer Pro | G10: 1 | H10: 331.94 | I10: 331.94 | J10: 189.98 | K10: 141.96 | L10: 2025-05
A11: 531178 | B11: 2025-08-29 | C11: Completed | D11: South | E11: Kitchenware | F11: Urbanox Dinnerware Set X | G11: 1 | H11: 101.22 | I11: 101.22 | J11: 59.39 | K11: 41.83 | L11: 2025-08
A12: 501771 | B12: 2023-03-16 | C12: Completed | D12: Southwest | E12: Home Decor | F12: Vantek Throw Pillow Lite | G12: 2 | H12: 210.1 | I12: 420.2 | J12: 247.66 | K12: 172.54 | L12: 2023-03
A13: 536486 | B13: 2025-12-13 | C13: Completed | D13: Northeast | E13: Kitchenware | F13: Aurora Cutting Board Pro | G13: 1 | H13: 185.24 | I13: 185.24 | J13: 104.87 | K13: 80.37 | L13: 2025-12
... A501: 530847 | B501: 2025-08-18 | C501: Completed | D501: Northeast | E501: Home Appliances | F501: PrimeLiving Vacuum Cleaner Max | G501: 1 | H501: 254.19 | I501: 254.19 | J501: 149.37 | K501: 104.82 | L501: 2025-08

Sheet Pivot Summary
A1: Revenue by Region x Category (Pivot-Style Summary)
A2: Built with SUMIFS formulas referencing 'Transaction Sample' — right-click any cell range and Insert > PivotTable to convert to a native Excel PivotTable from this same source data.
A4: Region | B4: Electronics | C4: Furniture | D4: Home Appliances | E4: Home Decor | F4: Kitchenware | G4: Outdoor & Garden | H4: Grand Total
A5: Midwest | B5: =SUMIFS('Transaction Sample'!$I$2:$I$501,'Transaction Sample'!$D$2:$D$501,$A5,'Transaction Sample'!$E$2:$E$501,B$4) -> 25050.28 | C5: =SUMIFS('Transaction Sample'!$I$2:$I$501,'Transaction Sample'!$D$2:$D$501,$A5,'Transaction Sample'!$E$2:$E$501,C$4) -> 5833.25 | D5: =SUMIFS('Transaction Sample'!$I$2:$I$501,'Transaction Sample'!$D$2:$D$501,$A5,'Transaction Sample'!$E$2:$E$501,D$4) -> 9123.36 | E5: =SUMIFS('Transaction Sample'!$I$2:$I$501,'Transaction Sample'!$D$2:$D$501,$A5,'Transaction Sample'!$E$2:$E$501,E$4) -> 2759.88 | F5: =SUMIFS('Transaction Sample'!$I$2:$I$501,'Transaction Sample'!$D$2:$D$501,$A5,'Transaction Sample'!$E$2:$E$501,F$4) -> 2611.43 | G5: =SUMIFS('Transaction Sample'!$I$2:$I$501,'Transaction Sample'!$D$2:$D$501,$A5,'Transaction Sample'!$E$2:$E$501,G$4) -> 6208.68 | H5: =SUM(B5:G5) -> 51586.88
A6: Northeast | B6: =SUMIFS('Transaction Sample'!$I$2:$I$501,'Transaction Sample'!$D$2:$D$501,$A6,'Transaction Sample'!$E$2:$E$501,B$4) -> 23129.54 | C6: =SUMIFS('Transaction Sample'!$I$2:$I$501,'Transaction Sample'!$D$2:$D$501,$A6,'Transaction Sample'!$E$2:$E$501,C$4) -> 5810.01 | D6: =SUMIFS('Transaction Sample'!$I$2:$I$501,'Transaction Sample'!$D$2:$D$501,$A6,'Transaction Sample'!$E$2:$E$501,D$4) -> 3655.66 | E6: =SUMIFS('Transaction Sample'!$I$2:$I$501,'Transaction Sample'!$D$2:$D$501,$A6,'Transaction Sample'!$E$2:$E$501,E$4) -> 2563.09 | F6: =SUMIFS('Transaction Sample'!$I$2:$I$501,'Transaction Sample'!$D$2:$D$501,$A6,'Transaction Sample'!$E$2:$E$501,F$4) -> 1669.96 | G6: =SUMIFS('Transaction Sample'!$I$2:$I$501,'Transaction Sample'!$D$2:$D$501,$A6,'Transaction Sample'!$E$2:$E$501,G$4) -> 4943.76 | H6: =SUM(B6:G6) -> 41772.02
A7: South | B7: =SUMIFS('Transaction Sample'!$I$2:$I$501,'Transaction Sample'!$D$2:$D$501,$A7,'Transaction Sample'!$E$2:$E$501,B$4) -> 41614.62 | C7: =SUMIFS('Transaction Sample'!$I$2:$I$501,'Transaction Sample'!$D$2:$D$501,$A7,'Transaction Sample'!$E$2:$E$501,C$4) -> 13053.26 | D7: =SUMIFS('Transaction Sample'!$I$2:$I$501,'Transaction Sample'!$D$2:$D$501,$A7,'Transaction Sample'!$E$2:$E$501,D$4) -> 5663.48 | E7: =SUMIFS('Transaction Sample'!$I$2:$I$501,'Transaction Sample'!$D$2:$D$501,$A7,'Transaction Sample'!$E$2:$E$501,E$4) -> 3011.57 | F7: =SUMIFS('Transaction Sample'!$I$2:$I$501,'Transaction Sample'!$D$2:$D$501,$A7,'Transaction Sample'!$E$2:$E$501,F$4) -> 3637.6 | G7: =SUMIFS('Transaction Sample'!$I$2:$I$501,'Transaction Sample'!$D$2:$D$501,$A7,'Transaction Sample'!$E$2:$E$501,G$4) -> 8934.08 | H7: =SUM(B7:G7) -> 75914.61
A8: Southwest | B8: =SUMIFS('Transaction Sample'!$I$2:$I$501,'Transaction Sample'!$D$2:$D$501,$A8,'Transaction Sample'!$E$2:$E$501,B$4) -> 28060.14 | C8: =SUMIFS('Transaction Sample'!$I$2:$I$501,'Transaction Sample'!$D$2:$D$501,$A8,'Transaction Sample'!$E$2:$E$501,C$4) -> 6564.02 | D8: =SUMIFS('Transaction Sample'!$I$2:$I$501,'Transaction Sample'!$D$2:$D$501,$A8,'Transaction Sample'!$E$2:$E$501,D$4) -> 8073.17 | E8: =SUMIFS('Transaction Sample'!$I$2:$I$501,'Transaction Sample'!$D$2:$D$501,$A8,'Transaction Sample'!$E$2:$E$501,E$4) -> 2991.62 | F8: =SUMIFS('Transaction Sample'!$I$2:$I$501,'Transaction Sample'!$D$2:$D$501,$A8,'Transaction Sample'!$E$2:$E$501,F$4) -> 3684.22 | G8: =SUMIFS('Transaction Sample'!$I$2:$I$501,'Transaction Sample'!$D$2:$D$501,$A8,'Transaction Sample'!$E$2:$E$501,G$4) -> 8131.05 | H8: =SUM(B8:G8) -> 57504.22
A9: West | B9: =SUMIFS('Transaction Sample'!$I$2:$I$501,'Transaction Sample'!$D$2:$D$501,$A9,'Transaction Sample'!$E$2:$E$501,B$4) -> 19690.87 | C9: =SUMIFS('Transaction Sample'!$I$2:$I$501,'Transaction Sample'!$D$2:$D$501,$A9,'Transaction Sample'!$E$2:$E$501,C$4) -> 8351.37 | D9: =SUMIFS('Transaction Sample'!$I$2:$I$501,'Transaction Sample'!$D$2:$D$501,$A9,'Transaction Sample'!$E$2:$E$501,D$4) -> 5200.35 | E9: =SUMIFS('Transaction Sample'!$I$2:$I$501,'Transaction Sample'!$D$2:$D$501,$A9,'Transaction Sample'!$E$2:$E$501,E$4) -> 2977.9 | F9: =SUMIFS('Transaction Sample'!$I$2:$I$501,'Transaction Sample'!$D$2:$D$501,$A9,'Transaction Sample'!$E$2:$E$501,F$4) -> 2835.67 | G9: =SUMIFS('Transaction Sample'!$I$2:$I$501,'Transaction Sample'!$D$2:$D$501,$A9,'Transaction Sample'!$E$2:$E$501,G$4) -> 3211.5 | H9: =SUM(B9:G9) -> 42267.66
A10: Grand Total | B10: =SUM(B5:B9) -> 137545.45 | C10: =SUM(C5:C9) -> 39611.91 | D10: =SUM(D5:D9) -> 31716.02 | E10: =SUM(E5:E9) -> 14304.06 | F10: =SUM(F5:F9) -> 14438.88 | G10: =SUM(G5:G9) -> 31429.07 | H10: =SUM(H5:H9) -> 269045.39

Sheet Monthly Trend
A1: Monthly Revenue, Profit & Margin (Pivot-Style Summary)
A3: Month | B3: Revenue | C3: Profit | D3: Margin %
A4: 2023-01 | B4: =SUMIFS('Transaction Sample'!$I$2:$I$501,'Transaction Sample'!$L$2:$L$501,A4) -> 1882.97 | C4: =SUMIFS('Transaction Sample'!$K$2:$K$501,'Transaction Sample'!$L$2:$L$501,A4) -> 812.53 | D4: =C4/B4 -> 0.43151511
A5: 2023-02 | B5: =SUMIFS('Transaction Sample'!$I$2:$I$501,'Transaction Sample'!$L$2:$L$501,A5) -> 9249.79 | C5: =SUMIFS('Transaction Sample'!$K$2:$K$501,'Transaction Sample'!$L$2:$L$501,A5) -> 3945.65 | D5: =C5/B5 -> 0.42656644
A6: 2023-03 | B6: =SUMIFS('Transaction Sample'!$I$2:$I$501,'Transaction Sample'!$L$2:$L$501,A6) -> 7043.7 | C6: =SUMIFS('Transaction Sample'!$K$2:$K$501,'Transaction Sample'!$L$2:$L$501,A6) -> 2993.63 | D6: =C6/B6 -> 0.42500816
A7: 2023-04 | B7: =SUMIFS('Transaction Sample'!$I$2:$I$501,'Transaction Sample'!$L$2:$L$501,A7) -> 4197.16 | C7: =SUMIFS('Transaction Sample'!$K$2:$K$501,'Transaction Sample'!$L$2:$L$501,A7) -> 1774.24 | D7: =C7/B7 -> 0.42272394
A8: 2023-05 | B8: =SUMIFS('Transaction Sample'!$I$2:$I$501,'Transaction Sample'!$L$2:$L$501,A8) -> 7671.86 | C8: =SUMIFS('Transaction Sample'!$K$2:$K$501,'Transaction Sample'!$L$2:$L$501,A8) -> 3268.74 | D8: =C8/B8 -> 0.42606878
A9: 2023-06 | B9: =SUMIFS('Transaction Sample'!$I$2:$I$501,'Transaction Sample'!$L$2:$L$501,A9) -> 5012.91 | C9: =SUMIFS('Transaction Sample'!$K$2:$K$501,'Transaction Sample'!$L$2:$L$501,A9) -> 2185.87 | D9: =C9/B9 -> 0.43604812
A10: 2023-07 | B10: =SUMIFS('Transaction Sample'!$I$2:$I$501,'Transaction Sample'!$L$2:$L$501,A10) -> 5697.8 | C10: =SUMIFS('Transaction Sample'!$K$2:$K$501,'Transaction Sample'!$L$2:$L$501,A10) -> 2437.51 | D10: =C10/B10 -> 0.42779845
A11: 2023-08 | B11: =SUMIFS('Transaction Sample'!$I$2:$I$501,'Transaction Sample'!$L$2:$L$501,A11) -> 8350.35 | C11: =SUMIFS('Transaction Sample'!$K$2:$K$501,'Transaction Sample'!$L$2:$L$501,A11) -> 3473.12 | D11: =C11/B11 -> 0.41592508
A12: 2023-09 | B12: =SUMIFS('Transaction Sample'!$I$2:$I$501,'Transaction Sample'!$L$2:$L$501,A12) -> 5126.72 | C12: =SUMIFS('Transaction Sample'!$K$2:$K$501,'Transaction Sample'!$L$2:$L$501,A12) -> 2174.89 | D12: =C12/B12 -> 0.42422641
A13: 2023-10 | B13: =SUMIFS('Transaction Sample'!$I$2:$I$501,'Transaction Sample'!$L$2:$L$501,A13) -> 4538.96 | C13: =SUMIFS('Transaction Sample'!$K$2:$K$501,'Transaction Sample'!$L$2:$L$501,A13) -> 1946.26 | D13: =C13/B13 -> 0.42878985
A14: 2023-11 | B14: =SUMIFS('Transaction Sample'!$I$2:$I$501,'Transaction Sample'!$L$2:$L$501,A14) -> 18054.43 | C14: =SUMIFS('Transaction Sample'!$K$2:$K$501,'Transaction Sample'!$L$2:$L$501,A14) -> 7740.3 | D14: =C14/B14 -> 0.42872026
A15: 2023-12 | B15: =SUMIFS('Transaction Sample'!$I$2:$I$501,'Transaction Sample'!$L$2:$L$501,A15) -> 15890.67 | C15: =SUMIFS('Transaction Sample'!$K$2:$K$501,'Transaction Sample'!$L$2:$L$501,A15) -> 6805.31 | D15: =C15/B15 -> 0.42825822
... A39: 2025-12 | B39: =SUMIFS('Transaction Sample'!$I$2:$I$501,'Transaction Sample'!$L$2:$L$501,A39) -> 23344.8 | C39: =SUMIFS('Transaction Sample'!$K$2:$K$501,'Transaction Sample'!$L$2:$L$501,A39) -> 9979.89 | D39: =C39/B39 -> 0.42749949

Sheet Lookup Demo
A1: Product Lookup — VLOOKUP & INDEX/MATCH Demo
A2: Enter a Product ID in the yellow cell below to look up its details.
A4: product_id | B4: product_name | C4: category | D4: unit_cost | E4: unit_price
A5: 140 | B5: PrimeLiving Knife Set Lite | C5: Kitchenware | D5: 84.96 | E5: 154.47
A6: 181 | B6: HomeCraft Grill Max | C6: Outdoor & Garden | D6: 138.59 | E6: 251.98
A7: 166 | B7: CoreHome Throw Pillow Max | C7: Home Decor | D7: 135.28 | E7: 245.96
A8: 192 | B8: Lumeo Garden Tools Kit Lite | C8: Outdoor & Garden | D8: 279.62 | E8: 508.4
A9: 208 | B9: Lumeo Patio Set X | C9: Outdoor & Garden | D9: 365.42 | E9: 664.4
A10: 43 | B10: Nexa Bluetooth Speaker Lite | C10: Electronics | D10: 155.57 | E10: 282.85
A11: 133 | B11: Nexa Mixing Bowls Max | C11: Kitchenware | D11: 94.24 | E11: 171.35
A12: 99 | B12: Lumeo Bookshelf Max | C12: Furniture | D12: 346.91 | E12: 630.75
A13: 56 | B13: HomeCraft Smart Watch Classic | C13: Electronics | D13: 720.81 | E13: 1310.56
A14: 209 | B14: PrimeLiving Outdoor Heater Classic | C14: Outdoor & Garden | D14: 190.82 | E14: 346.95
A15: 81 | B15: Nexa Sofa | C15: Furniture | D15: 211.76 | E15: 385.02
A16: 97 | B16: HomeCraft Bookshelf Lite | C16: Furniture | D16: 407.73 | E16: 741.33
A19: Lookup Product ID: | B19: 140
A20: Product Name (VLOOKUP): | B20: =VLOOKUP(B19,A5:E16,2,FALSE()) -> PrimeLiving Knife Set Lite
A21: Category (VLOOKUP): | B21: =VLOOKUP(B19,A5:E16,3,FALSE()) -> Kitchenware
A22: Unit Price (INDEX/MATCH): | B22: =INDEX(E5:E16,MATCH(B19,A5:A16,0)) -> 154.47
A24: Note: | B24: INDEX/MATCH above is the pre-2019 equivalent of XLOOKUP =XLOOKUP(B19,A5:A16,E5:E16) — shown as INDEX/MATCH for compatibility with older Excel versions and this file's verification tooling.
